figura/__init__.py
figura/cli.py
figura/container.py
figura/errors.py
figura/importutils.py
figura/misc.py
figura/override.py
figura/parser.py
figura/path.py
figura/settings.py
figura/utils.py
figura/version.py
figura/polyloader/__init__.py
figura/polyloader/_python2.py
figura/polyloader/_python3.py
figura/tools/__init__.py
figura/tools/figura_print.py
figura-1.2.4.dist-info/DESCRIPTION.rst
figura-1.2.4.dist-info/METADATA
figura-1.2.4.dist-info/RECORD
figura-1.2.4.dist-info/WHEEL
figura-1.2.4.dist-info/entry_points.txt
figura-1.2.4.dist-info/metadata.json
figura-1.2.4.dist-info/top_level.txt
